PYroMat-2.0.6.data/data/CHANGELOG.md
PYroMat-2.0.6.data/data/LICENSE.txt
PYroMat-2.0.6.data/data/README.md
PYroMat-2.0.6.data/data/test.py
PYroMat-2.0.6.dist-info/DESCRIPTION.rst
PYroMat-2.0.6.dist-info/METADATA
PYroMat-2.0.6.dist-info/RECORD
PYroMat-2.0.6.dist-info/WHEEL
PYroMat-2.0.6.dist-info/metadata.json
PYroMat-2.0.6.dist-info/top_level.txt
pyromat/__init__.py
pyromat/dat.py
pyromat/defaults.py
pyromat/reg.py
pyromat/solve.py
pyromat/units.py
pyromat/utility.py
pyromat/data/ig/Al.hpd
pyromat/data/ig/Al2_O.hpd
pyromat/data/ig/Al_Br3.hpd
pyromat/data/ig/Al_Cl3.hpd
pyromat/data/ig/Al_F.hpd
pyromat/data/ig/Al_F3.hpd
pyromat/data/ig/Al_H.hpd
pyromat/data/ig/Al_I3.hpd
pyromat/data/ig/Al_O.hpd
pyromat/data/ig/Ar.hpd
pyromat/data/ig/B.hpd
pyromat/data/ig/B10_H14.hpd
pyromat/data/ig/B2_H6.hpd
pyromat/data/ig/B2_O3.hpd
pyromat/data/ig/B3_F3_O3.hpd
pyromat/data/ig/B3_H3_O3.hpd
pyromat/data/ig/B3_H6_N3.hpd
pyromat/data/ig/B5_H9.hpd
pyromat/data/ig/B_Br3.hpd
pyromat/data/ig/B_Cl3.hpd
pyromat/data/ig/B_F.hpd
pyromat/data/ig/B_F2.hpd
pyromat/data/ig/B_F3.hpd
pyromat/data/ig/B_F4_K.hpd
pyromat/data/ig/B_H.hpd
pyromat/data/ig/B_H3.hpd
pyromat/data/ig/B_H3_O3.hpd
pyromat/data/ig/B_H_O2.hpd
pyromat/data/ig/B_K_O2.hpd
pyromat/data/ig/B_Li_O2.hpd
pyromat/data/ig/B_N.hpd
pyromat/data/ig/B_Na_O2.hpd
pyromat/data/ig/B_O.hpd
pyromat/data/ig/B_O2.hpd
pyromat/data/ig/Ba.hpd
pyromat/data/ig/Ba_Br2.hpd
pyromat/data/ig/Ba_Cl2.hpd
pyromat/data/ig/Ba_F.hpd
pyromat/data/ig/Ba_F2.hpd
pyromat/data/ig/Ba_H2_O2.hpd
pyromat/data/ig/Ba_I2.hpd
pyromat/data/ig/Ba_O.hpd
pyromat/data/ig/Ba_S.hpd
pyromat/data/ig/Be.hpd
pyromat/data/ig/Be_Cl2.hpd
pyromat/data/ig/Be_F.hpd
pyromat/data/ig/Be_F2.hpd
pyromat/data/ig/Be_H.hpd
pyromat/data/ig/Be_H2_O2.hpd
pyromat/data/ig/Be_O.hpd
pyromat/data/ig/Be_S.hpd
pyromat/data/ig/Br.hpd
pyromat/data/ig/Br2.hpd
pyromat/data/ig/Br2_Ca.hpd
pyromat/data/ig/Br2_Fe.hpd
pyromat/data/ig/Br2_Hg.hpd
pyromat/data/ig/Br2_Mg.hpd
pyromat/data/ig/Br2_Pb.hpd
pyromat/data/ig/Br2_Sr.hpd
pyromat/data/ig/Br3_P.hpd
pyromat/data/ig/Br4_Si.hpd
pyromat/data/ig/Br4_Ti.hpd
pyromat/data/ig/Br5_Nb.hpd
pyromat/data/ig/Br5_W.hpd
