Metadata-Version: 2.0
Name: PYroMat
Version: 2.0.6
Summary: Thermodynamic properties in Python.
Home-page: https://chmarti1.github.io/PYroMat/
Author: Chris Martin
Author-email: crm28@psu.edu
License: GNU General Public License v3 (GPLv3)
Keywords: thermodynamic properties
Platform: UNKNOWN
Classifier: Development Status :: 5 - Production/Stable
Classifier: Intended Audience :: Education
Classifier: Intended Audience :: End Users/Desktop
Classifier: Intended Audience :: Manufacturing
Classifier: Intended Audience :: Science/Research
Classifier: Topic :: Scientific/Engineering :: Physics
Classifier: Topic :: Scientific/Engineering :: Chemistry
Classifier: Topic :: Scientific/Engineering :: Atmospheric Science
Classifier: Natural Language :: English
Classifier: Programming Language :: Python :: 2
Classifier: Programming Language :: Python :: 3
Provides: pyromat
Requires-Dist: numpy (>=1.7)
